CHANGELOG.txt
LICENSE.txt
MANIFEST.in
README.txt
setup.py
kafkaproducerself/__init__.py
kafkaproducerself/producer.py
kafkaproducerself.egg-info/PKG-INFO
kafkaproducerself.egg-info/SOURCES.txt
kafkaproducerself.egg-info/dependency_links.txt
kafkaproducerself.egg-info/requires.txt
kafkaproducerself.egg-info/top_level.txt
venv/bin/activate_this.py
venv/lib/python3.10/site-packages/_virtualenv.py
venv/lib/python3.10/site-packages/_distutils_hack/__init__.py
venv/lib/python3.10/site-packages/_distutils_hack/override.py
venv/lib/python3.10/site-packages/kafka/__init__.py
venv/lib/python3.10/site-packages/kafka/client_async.py
venv/lib/python3.10/site-packages/kafka/cluster.py
venv/lib/python3.10/site-packages/kafka/codec.py
venv/lib/python3.10/site-packages/kafka/conn.py
venv/lib/python3.10/site-packages/kafka/errors.py
venv/lib/python3.10/site-packages/kafka/future.py
venv/lib/python3.10/site-packages/kafka/scram.py
venv/lib/python3.10/site-packages/kafka/structs.py
venv/lib/python3.10/site-packages/kafka/util.py
venv/lib/python3.10/site-packages/kafka/version.py
venv/lib/python3.10/site-packages/kafka/admin/__init__.py
venv/lib/python3.10/site-packages/kafka/admin/acl_resource.py
venv/lib/python3.10/site-packages/kafka/admin/client.py
venv/lib/python3.10/site-packages/kafka/admin/config_resource.py
venv/lib/python3.10/site-packages/kafka/admin/new_partitions.py
venv/lib/python3.10/site-packages/kafka/admin/new_topic.py
venv/lib/python3.10/site-packages/kafka/consumer/__init__.py
venv/lib/python3.10/site-packages/kafka/consumer/fetcher.py
venv/lib/python3.10/site-packages/kafka/consumer/group.py
venv/lib/python3.10/site-packages/kafka/consumer/subscription_state.py
venv/lib/python3.10/site-packages/kafka/coordinator/__init__.py
venv/lib/python3.10/site-packages/kafka/coordinator/base.py
venv/lib/python3.10/site-packages/kafka/coordinator/consumer.py
venv/lib/python3.10/site-packages/kafka/coordinator/heartbeat.py
venv/lib/python3.10/site-packages/kafka/coordinator/protocol.py
venv/lib/python3.10/site-packages/kafka/coordinator/assignors/__init__.py
venv/lib/python3.10/site-packages/kafka/coordinator/assignors/abstract.py
venv/lib/python3.10/site-packages/kafka_python-2.0.2.dist-info/top_level.txt
venv/lib/python3.10/site-packages/pip-23.1.2.dist-info/AUTHORS.txt
venv/lib/python3.10/site-packages/pip-23.1.2.dist-info/LICENSE.txt
venv/lib/python3.10/site-packages/pip-23.1.2.dist-info/entry_points.txt
venv/lib/python3.10/site-packages/pip-23.1.2.dist-info/top_level.txt
venv/lib/python3.10/site-packages/setuptools-68.0.0.dist-info/entry_points.txt
venv/lib/python3.10/site-packages/setuptools-68.0.0.dist-info/top_level.txt
venv/lib/python3.10/site-packages/wheel-0.40.0.dist-info/LICENSE.txt
venv/lib/python3.10/site-packages/wheel-0.40.0.dist-info/entry_points.txt
