Metadata-Version: 2.1
Name: kafkaproducerself
Version: 0.0.5
Summary: produce events to kafka
Home-page: UNKNOWN
Author: Abhishek Borana
Author-email: tracer.domanik@fixedfor.com
License: MIT
Keywords: kafka
Platform: UNKNOWN
License-File: LICENSE.txt
